LICENSE
MANIFEST.in
README.md
pyproject.toml
setup.py
pycommute.egg-info/PKG-INFO
pycommute.egg-info/SOURCES.txt
pycommute.egg-info/dependency_links.txt
pycommute.egg-info/not-zip-safe
pycommute.egg-info/requires.txt
pycommute.egg-info/top_level.txt
src/libcommute/libcommute/algebra_ids.hpp
src/libcommute/libcommute/libcommute.hpp
src/libcommute/libcommute/metafunctions.hpp
src/libcommute/libcommute/scalar_traits.hpp
src/libcommute/libcommute/utility.hpp
src/libcommute/libcommute/version.hpp
src/libcommute/libcommute/expression/dyn_indices.hpp
src/libcommute/libcommute/expression/expression.hpp
src/libcommute/libcommute/expression/factories.hpp
src/libcommute/libcommute/expression/factories_dyn.hpp
src/libcommute/libcommute/expression/generator.hpp
src/libcommute/libcommute/expression/generator_boson.hpp
src/libcommute/libcommute/expression/generator_fermion.hpp
src/libcommute/libcommute/expression/generator_spin.hpp
src/libcommute/libcommute/expression/hc.hpp
src/libcommute/libcommute/expression/monomial.hpp
src/libcommute/libcommute/loperator/bit_ops.hpp
src/libcommute/libcommute/loperator/compressed_state_view.hpp
src/libcommute/libcommute/loperator/disjoint_sets.hpp
src/libcommute/libcommute/loperator/elementary_space.hpp
src/libcommute/libcommute/loperator/elementary_space_boson.hpp
src/libcommute/libcommute/loperator/elementary_space_fermion.hpp
src/libcommute/libcommute/loperator/elementary_space_spin.hpp
src/libcommute/libcommute/loperator/es_constructor.hpp
src/libcommute/libcommute/loperator/hilbert_space.hpp
src/libcommute/libcommute/loperator/loperator.hpp
src/libcommute/libcommute/loperator/mapped_basis_view.hpp
src/libcommute/libcommute/loperator/monomial_action.hpp
src/libcommute/libcommute/loperator/monomial_action_boson.hpp
src/libcommute/libcommute/loperator/monomial_action_fermion.hpp
src/libcommute/libcommute/loperator/monomial_action_spin.hpp
src/libcommute/libcommute/loperator/n_fermion_sector_view.hpp
src/libcommute/libcommute/loperator/space_partition.hpp
src/libcommute/libcommute/loperator/sparse_state_vector.hpp
src/libcommute/libcommute/loperator/state_vector.hpp
src/libcommute/libcommute/loperator/state_vector_eigen3.hpp
