Metadata-Version: 2.4
Name: pycommute
Version: 1.0.0
Summary: Python bindings for the libcommute C++ library
Home-page: https://krivenko.github.io/pycommute
Author: Igor Krivenko
Author-email: iskrivenko@proton.me
License: MPL-2.0
Project-URL: Bug Tracker, https://github.com/krivenko/pycommute/issues
Project-URL: Documentation, https://krivenko.github.io/pycommute
Project-URL: Source Code, https://github.com/krivenko/pycommute
Keywords: libcommute dsl algebra quantum qubit
Classifier: Development Status :: 5 - Production/Stable
Classifier: Programming Language :: Python
Classifier: Programming Language :: Python :: 3
Classifier: Programming Language :: Python :: 3.8
Classifier: Programming Language :: Python :: 3.9
Classifier: Programming Language :: Python :: 3.10
Classifier: Programming Language :: Python :: 3.11
Classifier: Programming Language :: Python :: 3.12
Classifier: Programming Language :: Python :: 3.13
Classifier: Programming Language :: Python :: 3.14
Classifier: Topic :: Scientific/Engineering :: Physics
Requires-Python: >=3.8
License-File: LICENSE
Requires-Dist: numpy>=1.12.0
Dynamic: author
Dynamic: author-email
Dynamic: classifier
Dynamic: description
Dynamic: description-content-type
Dynamic: home-page
Dynamic: keywords
Dynamic: license
Dynamic: license-file
Dynamic: project-url
Dynamic: requires-dist
Dynamic: requires-python
Dynamic: summary
